movie_file_fixer/__init__.py
movie_file_fixer/__main__.py
movie_file_fixer/file_remover.py
movie_file_fixer/folderizer.py
movie_file_fixer/formatter.py
movie_file_fixer/movie_file_fixer.py
movie_file_fixer/poster_finder.py
movie_file_fixer/subtitle_finder.py
tests/__init__.py
tests/blockbuster.py
tests/test_movie_file_fixer.py
tests/test_utils.py
tests/test_examples/__init__.py
utils/__init__.py
utils/utils.py
movie_file_fixer-0.3.0.dist-info/LICENSE
movie_file_fixer-0.3.0.dist-info/METADATA
movie_file_fixer-0.3.0.dist-info/WHEEL
movie_file_fixer-0.3.0.dist-info/top_level.txt
movie_file_fixer-0.3.0.dist-info/RECORD
