Metadata-Version: 2.1
Name: movie-file-fixer
Version: 0.3.0
Summary: Given a directory of poorly formatted movie files, `movie-file-fixer` will create a beautifully formatted library of films folders, complete with posters, subtitles, and IMDb metadata.
Home-page: https://github.com/blairg23/movie-file-fixer
Author: Blair Gemmer
Author-email: blair@intelligen.technology
Maintainer: Blair Gemmer
Maintainer-email: blair@intelligen.technology
License: MIT
Project-URL: Source, https://github.com/blairg23/movie-file-fixer
Project-URL: Tracker, https://github.com/blairg23/movie-file-fixer/issues
Keywords: movies television backups multimedia omdb api imdb metadata
Platform: any
Classifier: Development Status :: 2 - Pre-Alpha
Classifier: Environment :: Web Environment
Classifier: Intended Audience :: Developers
Classifier: License :: OSI Approved :: MIT License
Classifier: Operating System :: OS Independent
Classifier: Programming Language :: Python
Classifier: Programming Language :: Python :: 3
Classifier: Programming Language :: Python :: 3.4
Classifier: Programming Language :: Python :: 3.5
Classifier: Programming Language :: Python :: 3.6
Classifier: Programming Language :: Python :: 3.7
Requires-Dist: fuzzywuzzy
Requires-Dist: omdbpy
Requires-Dist: python-Levenshtein
Requires-Dist: requests
Provides-Extra: testing
Requires-Dist: faker ; extra == 'testing'
Requires-Dist: pyfakefs ; extra == 'testing'
Requires-Dist: pytest-cov ; extra == 'testing'
Requires-Dist: pytest ; extra == 'testing'
Requires-Dist: tox ; extra == 'testing'
